mcp_perplexity/__init__.py
mcp_perplexity/database.py
mcp_perplexity/perplexity_client.py
mcp_perplexity/server.py
mcp_perplexity/web/__init__.py
mcp_perplexity/web/database_extension.py
mcp_perplexity/web/routes.py
mcp_perplexity/web/templates/_chat_list.html
mcp_perplexity/web/templates/_dialog.html
mcp_perplexity/web/templates/_message_list.html
mcp_perplexity/web/templates/base.html
mcp_perplexity/web/templates/chat.html
mcp_perplexity/web/templates/error.html
mcp_perplexity/web/templates/index.html
mcp_perplexity-0.6.0.dist-info/LICENSE
mcp_perplexity-0.6.0.dist-info/METADATA
mcp_perplexity-0.6.0.dist-info/WHEEL
mcp_perplexity-0.6.0.dist-info/entry_points.txt
mcp_perplexity-0.6.0.dist-info/top_level.txt
mcp_perplexity-0.6.0.dist-info/RECORD
