Metadata-Version: 2.2
Name: mcp-perplexity
Version: 0.6.0
Summary: MCP Server for the Perplexity API.
Author-email: Daniel Riccio <ricciodaniel98@gmail.com>
License: MIT
Project-URL: Homepage, https://github.com/daniel-lxs/mcp-perplexity
Project-URL: Repository, https://github.com/daniel-lxs/mcp-perplexity
Requires-Python: >=3.10
License-File: LICENSE
Requires-Dist: mcp>=1.0.0
Requires-Dist: httpx
Requires-Dist: haikunator>=2.1.0
Requires-Dist: quart>=0.19.4
Requires-Dist: sqlalchemy>=2.0.0
Requires-Dist: hypercorn>=0.15.0
Requires-Dist: markdown2>=2.4.0
Provides-Extra: dev
Requires-Dist: pyinstaller>=6.3.0; extra == "dev"
